fossil_delta/__init__.py
fossil_delta/_delta.abi3.so
fossil_delta/delta.c
fossil_delta/delta.h
fossil_delta/delta.py
fossil_delta/build/fossil_delta_build.py
python_fossil_delta-18.11.27.dist-info/LICENCE
python_fossil_delta-18.11.27.dist-info/METADATA
python_fossil_delta-18.11.27.dist-info/WHEEL
python_fossil_delta-18.11.27.dist-info/top_level.txt
python_fossil_delta-18.11.27.dist-info/RECORD
