Metadata-Version: 2.1
Name: python-fossil-delta
Version: 18.11.27
Summary: Delta compression algorithm from fossil SCM
Home-page: https://github.com/ggicci/python-fossil-delta
Author: Ggicci
Author-email: ggicci@163.com
License: MIT
Keywords: fossil-delta compression algorithm
Platform: any
Requires-Dist: cffi (>=1.11.5)
